MightyMaxims/GetRandom.py
MightyMaxims/Maxims.py
MightyMaxims/MightyMaxims2025.sqlt3
MightyMaxims/__init__.py
mightymaxims-2024.9.1.data/data/MightyMaxims/MightyMaxims2025.sqlt3
mightymaxims-2024.9.1.dist-info/METADATA
mightymaxims-2024.9.1.dist-info/WHEEL
mightymaxims-2024.9.1.dist-info/top_level.txt
mightymaxims-2024.9.1.dist-info/RECORD
