Metadata-Version: 2.4
Name: MightyMaxims
Version: 2024.9.1
Summary: Random Short & Memorable Quotations
Home-page: http://soft9000.com
Download-URL: https://github.com/soft9000/DoctorQuote
Author: Randall Nagy
Author-email: Randall Nagy <r.a.nagy@gmail.com>
Maintainer-email: Randall Nagy <r.a.nagy@gmail.com>
License-Expression: MIT
Project-URL: Homepage, https://github.com/soft9000/DoctorQuote
Project-URL: Bug Tracker, https://github.com/soft9000/DoctorQuote/issues
Platform: Cross-Platform CLI / TUI
Classifier: Programming Language :: Python :: 3
Requires-Python: >=3.6
Dynamic: author
Dynamic: download-url
Dynamic: home-page
Dynamic: platform
